ga_optimizer/__init__.py
ga_optimizer/make_optimizer.py
ga_optimizer/utils/__init__.py
ga_optimizer/utils/optimizers.py
ga_optimizer/utils/optimizers_temp.py
ga_optimizer/utils/utils.py
tests/__init__.py
tests/test_utils.py
tests/integration/__init__.py
tests/integration/test_optimizer_integration.py
tests/unit/__init__.py
tests/unit/test_simple_abc.py
ga_optimizer-0.1.2.dist-info/LICENSE
ga_optimizer-0.1.2.dist-info/METADATA
ga_optimizer-0.1.2.dist-info/WHEEL
ga_optimizer-0.1.2.dist-info/top_level.txt
ga_optimizer-0.1.2.dist-info/RECORD
