Metadata-Version: 2.1
Name: ga-optimizer
Version: 0.1.2
Summary: Gradient Accumulation Optimizer Wrapper for Keras/TensorFlow
Home-page: https://github.com/kimjansheden/ga-optimizer
Author: Kim Jansheden
Author-email: kim.jansheden@gmail.com
Classifier: Programming Language :: Python :: 3
Classifier: License :: OSI Approved :: MIT License
Classifier: Operating System :: OS Independent
Requires-Python: >=3.6
License-File: LICENSE
Requires-Dist: tensorflow >=2.0
